bfqry/__about__.py
bfqry/__init__.py
bfqry/__main__.py
bfqry/cli/__init__.py
bfqry/cli/common.py
bfqry/cli/parser.py
bfqry/cli/util.py
bfqry-2024.12.1.dist-info/METADATA
bfqry-2024.12.1.dist-info/WHEEL
bfqry-2024.12.1.dist-info/entry_points.txt
bfqry-2024.12.1.dist-info/licenses/LICENSE
bfqry-2024.12.1.dist-info/RECORD
