Metadata-Version: 2.3
Name: bfqry
Version: 2024.12.1
Summary: Batfish Query Utility
Project-URL: Documentation, https://github.com/sig9org/bfqry
Project-URL: Issues, https://github.com/sig9org/bfqry/issues
Project-URL: Source, https://github.com/sig9org/bfqry
Author-email: sig9 <sig9@sig9.org>
License: MIT
Keywords: batfish
Classifier: Development Status :: 4 - Beta
Classifier: Programming Language :: Python
Classifier: Programming Language :: Python :: 3.8
Classifier: Programming Language :: Python :: 3.9
Classifier: Programming Language :: Python :: 3.10
Classifier: Programming Language :: Python :: 3.11
Classifier: Programming Language :: Python :: 3.12
Classifier: Programming Language :: Python :: Implementation :: CPython
Classifier: Programming Language :: Python :: Implementation :: PyPy
Requires-Python: >=3.8
Requires-Dist: argcomplete
Requires-Dist: openpyxl
Requires-Dist: pybatfish
Requires-Dist: requests
Requires-Dist: setuptools
